{
  "书名": "三因",
  "朝代": "宋",
  "年代": "",
  "作者": "陈言",
  "主要思想": "**蜜附汤（可能为用户提问的“蜜附子汤”的误写）百科**\n\n蜜附汤是一款具有特定主治功效的中药方剂，以下是对其的详细介绍：\n\n### 一、基本信息\n\n- **名称**：蜜附汤\n- **处方来源**：《三因》卷九^[8][1]^\n- **主要功效**：主治心腹疼痛，或吐或泄，状如霍乱；及冒涉湿寒，贼风入腹，拘急切痛；疝气发作^[8][1]^\n\n### 二、药物组成\n\n蜜附汤的药物组成主要包括以下成分",
  "原文": "**蜜附汤（可能为用户提问的“蜜附子汤”的误写）百科**\n\n蜜附汤是一款具有特定主治功效的中药方剂，以下是对其的详细介绍：\n\n### 一、基本信息\n\n- **名称**：蜜附汤\n- **处方来源**：《三因》卷九^[8][1]^\n- **主要功效**：主治心腹疼痛，或吐或泄，状如霍乱；及冒涉湿寒，贼风入腹，拘急切痛；疝气发作^[8][1]^\n\n### 二、药物组成\n\n蜜附汤的药物组成主要包括以下成分^[8]^：\n\n- 附子（生，去皮脐，切作4片，以白蜜煎，令附子变色，以汤洗，去蜜，切）半两\n- 桂心3分\n- 芍药3分\n- 甘草（炙）4钱\n\n### 三、制备方法\n\n制备蜜附汤的方法为：将上述药物混合后，研为散剂^[8]^。\n\n### 四、用法用量\n\n服用蜜附汤时，每次取4大钱药物，加入水1盏，再加入生姜5片、大枣2枚，煎至7分后，去滓，于食前服用^[8]^。\n\n### 五、方剂解读\n\n- **附子**：附子为毛茛科植物乌头的子根炮制品，具有温经散寒、除湿解痛的功效^[7]^。在蜜附汤中，附子经过白蜜的炮制，其毒性得到缓和，同时保留了其温阳散寒的功效。\n- **桂心、芍药、甘草**：这些药物在方剂中起到辅助附子温阳散寒、调和气血的作用^[8]^。\n\n### 六、注意事项\n\n- 蜜附汤中的附子具有毒性，因此在制备和服用过程中需要严格控制剂量和煎煮时间，以防中毒^[3]^。\n- 服用蜜附汤前，建议咨询专业中医医师，根据个人体质和病情进行适当调整。\n\n### 七、临床应用\n\n蜜附汤在临床上主要用于治疗心腹疼痛、霍乱样症状、湿寒侵袭所致的拘急切痛以及疝气发作等疾病^[8][1]^。其温阳散寒、除湿解痛的功效在这些疾病的治疗中发挥着重要作用。\n\n综上所述，蜜附汤是一款具有特定主治功效的中药方剂，其药物组成、制备方法、用法用量以及注意事项等均需严格按照中医理论进行。在临床应用中，应根据患者具体情况进行适当调整，以确保疗效和安全。"
}