{
  "书名": "冯氏锦囊·外科",
  "朝代": "清",
  "年代": "1722",
  "作者": "冯兆张",
  "主要思想": "**《冯氏锦囊·外科》**\n\n**一、基本信息**\n\n《冯氏锦囊·外科》是清代医家冯兆张所著《冯氏锦囊秘录》中的一部分。该书初刊于清康熙六十一年（1722），是中医丛书中的重要著作^[6][1]^。\n\n**二、作者介绍**\n\n冯兆张，字楚瞻，浙江海盐人。他自幼习医，精于医术，后游医于天下，尤擅儿科。他推崇赵献可的命门之说，并集三十年之经验，著成《冯氏锦囊秘录》^[6]^。\n\n**三、内容概述**",
  "原文": "**《冯氏锦囊·外科》**\n\n**一、基本信息**\n\n《冯氏锦囊·外科》是清代医家冯兆张所著《冯氏锦囊秘录》中的一部分。该书初刊于清康熙六十一年（1722），是中医丛书中的重要著作^[6][1]^。\n\n**二、作者介绍**\n\n冯兆张，字楚瞻，浙江海盐人。他自幼习医，精于医术，后游医于天下，尤擅儿科。他推崇赵献可的命门之说，并集三十年之经验，著成《冯氏锦囊秘录》^[6]^。\n\n**三、内容概述**\n\n《冯氏锦囊·外科》是《冯氏锦囊秘录》中专门论述外科疾病的篇章。该书详细阐述了外科痈疽的治法，并强调痈疽证治以内补温阳为主^[7]^。此外，书中还收录了多个治疗外科疾病的方剂，如连翘解毒汤等，这些方剂具有清热毒、化湿邪等功效，主治四肢肿湿诸疮等疾病^[4][2]^。\n\n**四、学术价值**\n\n1. **系统性**：《冯氏锦囊·外科》作为《冯氏锦囊秘录》的一部分，具有系统性和综合性的特点。它涵盖了外科疾病的多个方面，为后世医者提供了丰富的临床经验和理论依据。\n2. **实用性**：该书中的方剂和治法经过临床验证，具有较高的实用性。许多方剂至今仍被中医临床所使用，为治疗外科疾病提供了有效的手段。\n3. **创新性**：冯兆张在《冯氏锦囊·外科》中提出了许多新的观点和治法，如强调内补温阳在痈疽证治中的重要性等，这些创新性的观点对后世中医外科的发展产生了深远的影响。\n\n**五、后世影响**\n\n《冯氏锦囊·外科》作为中医外科的重要著作，对后世中医外科的发展产生了深远的影响。它的学术思想和治法被后世医者广泛传承和应用，为中医外科的繁荣和发展做出了重要贡献。同时，该书也为中医临床提供了宝贵的经验和启示，为中医事业的传承和发展注入了新的活力。"
}