{
  "书名": "医学从众录",
  "朝代": "清",
  "年代": "1820",
  "作者": "陈修园",
  "主要思想": "**您可能想要查询的是《医学从众录》的百科信息，以下是对其的详细介绍**：\n\n### 一、基本信息\n\n《医学从众录》是清代陈修园（原名陈念祖）编撰的论治内科杂病的医书，初撰时曾托名叶桂，后收回用其本名^[6][5][4][2]^。该书成于嘉庆二十五年（1820年），共八卷，分39篇，论述近40种内科病证，且旁及妇人杂病^[6][5]^。\n\n### 二、内容特点\n\n- **详审脉证，深究病机**：该",
  "原文": "**您可能想要查询的是《医学从众录》的百科信息，以下是对其的详细介绍**：\n\n### 一、基本信息\n\n《医学从众录》是清代陈修园（原名陈念祖）编撰的论治内科杂病的医书，初撰时曾托名叶桂，后收回用其本名^[6][5][4][2]^。该书成于嘉庆二十五年（1820年），共八卷，分39篇，论述近40种内科病证，且旁及妇人杂病^[6][5]^。\n\n### 二、内容特点\n\n- **详审脉证，深究病机**：该书详审脉证，深究病机，辨证选方颇具特色。论治内科病证，多本医学经典之旨，从病机到治法，每引用《内经》或仲景学说有关内容加以阐释，或选用仲景的方药作为病证治疗的准则^[5]^。\n- **采各家之言，结合编者经验**：每篇先概叙病因、病机，次到治法方药。其中于各证摘选诸家精要，更参以编者经验^[5]^。\n- **文字简练，论理明晰**：全书文字简练，论理明晰，对临床辨证用药颇多启发，为后世医家所肯定^[2]^。\n\n### 三、版本与流传\n\n- **清道光25年刊行**：该书在清道光25年（即1845年）正式刊行^[5]^。\n- **多种版本流传**：现存20余种清刻本，1949年后有排印本^[6]^。此外，该书还被多次出版，如2012年天津科学技术出版社和2016年中国中医药出版社都曾出版过此书^[8][7]^。\n\n### 四、作者介绍\n\n- **陈修园（陈念祖）**：生于乾隆十八年（1753年），卒于道光三年（1823年），福建长乐（今福建省福州市长乐区江田镇溪湄村）人^[4]^。他自幼攻读儒经，同时学医，曾拜泉州名医蔡茗庄为师^[4]^。乾隆五十七年（1792年）中举，曾任直隶省威县知县等职^[4]^。在任上曾自选有效方剂救治水灾后罹患疫病的百姓^[4]^。嘉庆二十四年（1819年）以病告归，在福州石井巷井上草堂讲学，培养医学生^[4]^。\n\n### 五、价值与影响\n\n《医学从众录》作为清代名医陈修园的代表作之一，对后世医学产生了深远的影响。其详审脉证、深究病机的辨证选方方法，以及采各家之言、结合编者经验的论述方式，都为后世医家提供了宝贵的参考和启示。同时，该书的文字简练、论理明晰的特点，也使得其成为中医学习和研究的重要文献之一。\n\n请注意，由于您提供的书名可能存在笔误（应为《医学从众录》而非《医学从今录》），因此以上信息均基于《医学从众录》进行介绍。如仍有疑问或需要更多信息，请随时提问。"
}