{
  "书名": "外台秘要卷十所引延年秘录",
  "朝代": "唐",
  "年代": "752",
  "作者": "王焘",
  "主要思想": "### 《外台》卷十引《延年秘录》 百科\n\n**一、基本信息**\n\n- **书名**：《外台秘要》卷十所引《延年秘录》\n- **来源**：《外台秘要》是唐代王焘所著的综合性医书，而《延年秘录》则是其中引用的另一部古代医著的部分内容。\n- **时代背景**：唐代\n\n**二、书籍内容**\n\n- **主要内容**：《外台》卷十所引的《延年秘录》内容主要涉及中医方剂及其治疗方法。例如，其中记载的百部根饮，",
  "原文": "### 《外台》卷十引《延年秘录》 百科\n\n**一、基本信息**\n\n- **书名**：《外台秘要》卷十所引《延年秘录》\n- **来源**：《外台秘要》是唐代王焘所著的综合性医书，而《延年秘录》则是其中引用的另一部古代医著的部分内容。\n- **时代背景**：唐代\n\n**二、书籍内容**\n\n- **主要内容**：《外台》卷十所引的《延年秘录》内容主要涉及中医方剂及其治疗方法。例如，其中记载的百部根饮，就是用于治疗肺气客热、暴伤风寒、因嗽不安等症状的中医方剂^[2]^。\n- **方剂特点**：这些方剂通常具有明确的功效和主治病症，且用药讲究，配伍合理，体现了古代中医的智慧和经验。\n\n**三、引用情况**\n\n- **在《外台秘要》中的地位**：《延年秘录》作为《外台秘要》所引用的医著之一，为该书提供了丰富的方剂资源和治疗思路，是《外台秘要》的重要组成部分。\n- **对后世的影响**：《外台秘要》及其所引用的《延年秘录》等医著，对后世中医的发展产生了深远的影响，为中医临床提供了宝贵的经验和参考。\n\n**四、相关人物**\n\n- **王焘**：唐代著名医家，著有《外台秘要》。他博采众家之长，广泛引用前人的医籍和方剂，为中医的发展做出了重要贡献^[4]^。\n\n**五、总结**\n\n《外台》卷十所引的《延年秘录》是唐代中医方剂学的重要文献之一，为后世中医提供了宝贵的经验和参考。通过学习和研究这些方剂，我们可以更好地理解和运用中医的智慧，为人类的健康事业做出贡献。"
}