{
  "书名": "女科撮要",
  "朝代": "明",
  "年代": "1548",
  "作者": "薛己",
  "主要思想": "**《女科撮要》百科**\n\n《女科撮要》是一部重要的中医妇科专著，以下是对其的详细介绍：\n\n### 一、基本信息\n\n- **书名**：《女科撮要》^[10][4][1]^\n- **作者**：明·薛己^[10][4][2][1]^\n- **成书时间**：刊于1548年^[1]^\n- **主要内容**：全书共2卷，上卷涉及月经病、带下病、乳房病及前阴诸病等妇科常见病证，共15种，并附有各证方药；下卷则",
  "原文": "**《女科撮要》百科**\n\n《女科撮要》是一部重要的中医妇科专著，以下是对其的详细介绍：\n\n### 一、基本信息\n\n- **书名**：《女科撮要》^[10][4][1]^\n- **作者**：明·薛己^[10][4][2][1]^\n- **成书时间**：刊于1548年^[1]^\n- **主要内容**：全书共2卷，上卷涉及月经病、带下病、乳房病及前阴诸病等妇科常见病证，共15种，并附有各证方药；下卷则涵盖妊娠病、产时病及产后病等产科常见病证，同样为15种，附有各证方药，并列举了临床病案^[1]^。\n\n### 二、作者介绍\n\n- **薛己**：字新甫，号立斋，明代吴县（今江苏苏州）人。他世医出身，父亲薛铠是当时名医，任职太医院。薛己承续父业，闻名于时，先后任御医及太医院使。他精研医术，兼通内、外、妇、儿各科，名著一时^[8][2]^。\n\n### 三、书籍特点\n\n- **分类证治**：将妇科与产科疾病进行分类证治，是《女科撮要》的显著特点^[1]^。\n- **附方实用**：书中所选附方切合实用，可作为学习中医妇科的参考书^[7]^。\n- **病案列举**：列举了大量临床病案，有助于读者更好地理解和应用书中的理论知识^[1]^。\n\n### 四、版本与流传\n\n- **版本信息**：《宋氏女科撮要》是中国中医药出版社出版的图书，作者虽题为宋林皋，但此书与薛己所著的《女科撮要》在书名上相似，但内容并不相同，读者需注意区分^[10][4]^。\n- **流传情况**：《女科撮要》作为中医妇科的重要著作，自问世以来，一直受到医学界的重视和传承。其理论体系和治疗方法对后世中医妇科的发展产生了深远影响。\n\n### 五、总结\n\n《女科撮要》是明代薛己所著的一部中医妇科专著，具有分类证治、附方实用和病案列举等特点。其理论体系和治疗方法对后世中医妇科的发展具有重要意义。读者在阅读此书时，应注意与其他同名或相似书名的著作进行区分，以确保获取准确的信息。"
}