{
  "书名": "孙鲁川医案",
  "朝代": "无（或明/清等，因孙鲁川具体朝代未明确单一指向，但按家族传承可宽泛关联明清，此处按最严格对应信息填“无”）",
  "年代": "",
  "作者": "孙朝宗",
  "主要思想": "**孙氏医案 百科**\n\n**一、概述**\n\n孙氏医案，作为中医领域的重要文献，记录了孙氏家族多位医学家的临床经验和医案。这些医案不仅反映了孙氏家族在医学领域的深厚造诣，也为后世医者提供了宝贵的借鉴和参考。\n\n**二、主要医案作品**\n\n1. **《孙鲁川医案》**\n   - **作者**：孙朝宗（孙鲁川之子，孙氏医学第四代传人）\n   - **内容**：该书主要讲述了孙鲁川对医学的一些见解和方法",
  "原文": "**孙氏医案 百科**\n\n**一、概述**\n\n孙氏医案，作为中医领域的重要文献，记录了孙氏家族多位医学家的临床经验和医案。这些医案不仅反映了孙氏家族在医学领域的深厚造诣，也为后世医者提供了宝贵的借鉴和参考。\n\n**二、主要医案作品**\n\n1. **《孙鲁川医案》**\n   - **作者**：孙朝宗（孙鲁川之子，孙氏医学第四代传人）\n   - **内容**：该书主要讲述了孙鲁川对医学的一些见解和方法，涵盖了中风、痹病、痿病、头痛、眩晕、健忘、消渴等多种病症的医案^[7]^。\n   - **特点**：医案详细记录了孙鲁川的临床诊治经验，为后世医者提供了丰富的案例和思路。\n\n2. **《孙文垣医案》**\n   - **作者**：孙一奎（明代医学家，孙文垣为其字）及其子泰来、明来和学生余煌\n   - **内容**：该书汇集了孙一奎生前的250多则医案，涉及内科、外科、妇科、儿科等多个领域^[6][1]^。\n   - **特点**：医案全面展示了孙一奎的临床经验和医术，对后世医者具有极高的参考价值。\n\n**三、孙氏家族医学传承**\n\n孙氏家族在医学领域有着深厚的传承和造诣。从孙一奎到孙鲁川，再到孙朝宗，孙氏家族的医学传承已经历了多代。他们不仅在临床实践中积累了丰富的经验，还著书立说，为后世医者留下了宝贵的财富。\n\n**四、孙氏医案的影响**\n\n孙氏医案作为中医领域的重要文献，对后世医者产生了深远的影响。这些医案不仅为医者提供了丰富的临床案例和思路，还促进了中医理论的传承和发展。同时，孙氏医案也展示了孙氏家族在医学领域的卓越贡献和深厚造诣。\n\n**五、总结**\n\n孙氏医案是中医领域的重要文献之一，记录了孙氏家族多位医学家的临床经验和医案。这些医案不仅为后世医者提供了宝贵的借鉴和参考，还促进了中医理论的传承和发展。通过对孙氏医案的学习和研究，我们可以更深入地了解中医的精髓和魅力。"
}