{
  "书名": "宋氏女科秘书",
  "朝代": "明",
  "年代": "1612",
  "作者": "宋林皋",
  "主要思想": "# 《宋氏女科秘书》百科\n\n《宋氏女科秘书》是明代著名女科（妇科）医学家宋林皋撰写的一部中医著作。以下是对该书的详细介绍：\n\n## 一、基本信息\n\n- **书名**：《宋氏女科秘书》\n- **作者**：宋林皋\n- **成书时间**：约明万历四十年（1612年）^[1]^\n- **类别**：妇科类中医著作^[1]^\n\n## 二、作者介绍\n\n- **姓名**：宋林皋^[6][2]^\n- **时代**：",
  "原文": "# 《宋氏女科秘书》百科\n\n《宋氏女科秘书》是明代著名女科（妇科）医学家宋林皋撰写的一部中医著作。以下是对该书的详细介绍：\n\n## 一、基本信息\n\n- **书名**：《宋氏女科秘书》\n- **作者**：宋林皋\n- **成书时间**：约明万历四十年（1612年）^[1]^\n- **类别**：妇科类中医著作^[1]^\n\n## 二、作者介绍\n\n- **姓名**：宋林皋^[6][2]^\n- **时代**：明朝^[6][2]^\n- **籍贯**：明州（今浙江宁波）^[6][2]^\n- **主要成就**：以女科闻名于世，写成了中国古代女科集大成的《宋氏女科秘书》^[6][2]^\n\n宋林皋是明朝著名的女科医学家，活动于万历年间。他出身于医学世家，历经二十余世，以女科闻名于世。宋林皋遍览前代女科之书，结合自己的长期行医实践经验和深厚的家传，剔除前代及同类著作之鄙漏，留存可取之处，阐发精义，集历代女科之大成，撰写而成《宋氏女科秘书》^[2]^。\n\n## 三、书籍内容\n\n《宋氏女科秘书》全书不分卷，内容涵盖了妇科的经、带、胎、产诸病，并详细阐述了各种病症的治法及方剂^[5][1]^。书中载方众多，对妇科疾病的诊断和治疗具有极高的参考价值。\n\n## 四、方剂介绍\n\n《宋氏女科秘书》中记载了许多著名的中医方剂，如加味升麻葛根汤和清肺饮等^[7][4][3]^。\n\n- **加味升麻葛根汤**：主治产育艰难，或一岁一产。由升麻、葛根、芍药、甘草、瞿麦、土牛膝、瓜蒌根、豆豉（炒）等药物组成^[7][3]^。\n- **清肺饮**：具有清热止血之功效，主治妇人虚劳热发，咳嗽吐血。由当归、川芎、黄芩、贝母（去心）、知母（蜜水炒）、阿胶（炒成珠）、生地、蒲黄（炒）、陈皮等药物组成^[4]^。\n\n## 五、书籍影响\n\n《宋氏女科秘书》集历代女科之大成，对后世的妇科医学产生了深远的影响。该书不仅为当时的妇科医生提供了宝贵的参考，也为后世的中医妇科研究提供了重要的资料。\n\n综上所述，《宋氏女科秘书》是一部具有重要价值的中医妇科著作，值得广大中医爱好者和从业者深入学习和研究。"
}