{
  "书名": "实用中成药手册",
  "朝代": "（无朝代）",
  "年代": "2010",
  "作者": "许利平",
  "主要思想": "**《实用中成药手册》百科**\n\n**一、基本信息**\n\n《实用中成药手册》是一本关于中成药的实用手册，旨在为读者提供中成药的详细信息和使用指导。该书由许利平主编，于2010年由中国中医药出版社出版^[3][2]^。\n\n**二、内容概述**\n\n该手册是现有的中成药品种及其主要资料的汇编，内容涵盖了中成药的组成、规格、功效、主治、用法及注意事项等方面。手册中的中成药品种繁多，包括内科、外科、妇科、儿",
  "原文": "**《实用中成药手册》百科**\n\n**一、基本信息**\n\n《实用中成药手册》是一本关于中成药的实用手册，旨在为读者提供中成药的详细信息和使用指导。该书由许利平主编，于2010年由中国中医药出版社出版^[3][2]^。\n\n**二、内容概述**\n\n该手册是现有的中成药品种及其主要资料的汇编，内容涵盖了中成药的组成、规格、功效、主治、用法及注意事项等方面。手册中的中成药品种繁多，包括内科、外科、妇科、儿科、皮肤科、眼科、耳鼻喉科、口腔科等多个临床科室的常用中成药^[3][2]^。\n\n**三、特点与用途**\n\n1. **全面系统**：手册内容全面系统，涵盖了中成药的各个方面，为读者提供了全方位的中成药知识。\n2. **实用性强**：手册注重实用性，详细介绍了每种中成药的组成、规格、功效、主治、用法及注意事项，方便读者在实际应用中查阅。\n3. **适用人群广泛**：手册不仅适用于专业医务人员，也适用于普通消费者，为不同人群提供了方便的中成药使用指导。\n4. **参考价值高**：手册中的中成药资料详实可靠，具有较高的参考价值，可为中成药的研发、生产、销售和使用提供有力支持^[2]^。\n\n**四、版本与更新**\n\n随着医药产业的不断发展和新药的不断涌现，中成药的品种和数量也在不断增加。因此，《实用中成药手册》也需要不断更新和完善，以适应临床和市场的变化。读者在使用时，可以关注手册的最新版本和更新信息，以确保获取最准确、最全面的中成药知识。\n\n**五、总结**\n\n《实用中成药手册》是一本全面系统、实用性强、适用人群广泛、参考价值高的中成药手册。它为广大医务人员和普通消费者提供了方便的中成药使用指导，是中成药领域的重要参考资料。"
}