{
  "书名": "急救痧症全集",
  "朝代": "（无明确朝代信息，故空）",
  "年代": "",
  "作者": "",
  "主要思想": "**急救痧症全集 百科**\n\n由于直接名为“急救痧症全集”的详细百科资料可能难以直接提供，但根据与“痧症”相关的中医知识和文献，可以整理出一个关于痧症急救的综合性概述。\n\n### 一、痧症概述\n\n痧症，又称痧气、痧胀，是一种多发于夏秋季节的季节性病症，主要由感受风寒暑湿燥火六淫之邪气或疫疠秽浊毒气所引起。临床上以突然头晕、头痛、脘腹胀闷绞痛、欲吐不吐、欲泻不泻、四肢挛急、甚至昏厥、唇甲青紫等症状为",
  "原文": "**急救痧症全集 百科**\n\n由于直接名为“急救痧症全集”的详细百科资料可能难以直接提供，但根据与“痧症”相关的中医知识和文献，可以整理出一个关于痧症急救的综合性概述。\n\n### 一、痧症概述\n\n痧症，又称痧气、痧胀，是一种多发于夏秋季节的季节性病症，主要由感受风寒暑湿燥火六淫之邪气或疫疠秽浊毒气所引起。临床上以突然头晕、头痛、脘腹胀闷绞痛、欲吐不吐、欲泻不泻、四肢挛急、甚至昏厥、唇甲青紫等症状为特征，有时在肘窝、腋窝、颈前两旁会出现青紫痧筋^[1]^。\n\n### 二、急救方法\n\n1. **刮痧疗法**\n   - 刮痧是中医传统疗法之一，通过刮蹭皮肤，使皮肤下毛细血管破裂，瘀血渗透到皮肤中，造成淤青（即出痧），从而帮助宣泄邪气，达到治疗目的^[2]^。\n   - 刮痧过程中，局部出现痧迹后应改为轻刮法，使痧慢慢透发出来，以减轻疼痛，称为透痧^[2]^。\n\n2. **药物治疗**\n   - 中药方剂如升麻葛根汤合泻白散等可用于治疗痧症初起^[5]^。\n   - 特定药丹如治痧救命丹，由马牙消、雄黄、黄丹、朱砂等材料制成，也可用于治疗痧症^[6]^。\n\n3. **其他疗法**\n   - 拿法、砭法等也是治疗痧症的有效方法，但需在专业医师指导下进行^[4]^。\n\n### 三、相关文献\n\n1. **《痧症全生》**\n   - 清代黄鹤龄所著，主要介绍痧症简易有效的治疗方法，包括拿法、刮法、砭法及方药治疗诸法^[4]^。\n\n2. **《七十二种痧症救治法》**\n   - 近代陈景歧编著，选辑多部痧症相关著作，重新编次而成，详细介绍七十二种痧症的具体治疗方法^[3]^。\n\n### 四、注意事项\n\n- 痧症急救时，应迅速识别症状，并采取适当的急救措施。\n- 刮痧等疗法需在专业医师指导下进行，避免操作不当导致皮肤损伤或其他并发症。\n- 病情严重时，应及时就医，以免延误治疗。\n\n综上所述，“急救痧症全集”虽难以直接提供，但通过对痧症的概述、急救方法、相关文献及注意事项的整理，可以形成一个较为全面的急救痧症知识体系。"
}