{
  "书名": "由于提供的信息中未涉及书籍相关内容",
  "朝代": "无",
  "年代": "1912",
  "作者": "无",
  "主要思想": "**圣忠**可能是一个较为常见的名字，在不同领域有不同的人使用。以下是根据当前可获取的信息，对名为“圣忠”的人物、地点等进行的简要百科式介绍：\n\n### 人物\n\n1. **宣圣忠**（1912年-1932年2月）^[9]^\n   - 出生于安徽省金安区。\n   - 生前为战士，1932年2月在湖北省牺牲。\n\n2. **徐圣忠**（存在两个同名人物）\n   - **徐圣忠（1924年5月-1948年",
  "原文": "**圣忠**可能是一个较为常见的名字，在不同领域有不同的人使用。以下是根据当前可获取的信息，对名为“圣忠”的人物、地点等进行的简要百科式介绍：\n\n### 人物\n\n1. **宣圣忠**（1912年-1932年2月）^[9]^\n   - 出生于安徽省金安区。\n   - 生前为战士，1932年2月在湖北省牺牲。\n\n2. **徐圣忠**（存在两个同名人物）\n   - **徐圣忠（1924年5月-1948年2月）**^[8][2]^：\n\t - 出生于江苏省泰兴。\n\t - 生前是泰兴县独立团战士，1948年2月牺牲。\n   - **另一徐圣忠**（信息未详）：可能还有其他名为徐圣忠的人物，在当前搜索结果中未详细列出。\n\n3. **谢圣忠**^[14][4]^\n   - 汉族，1976年11月生，福建南靖人。\n   - 专注于企业环境、民宿酒店及别墅设计，是金蜘蛛（苏州）建筑装饰设计工程有限公司的创始人、室内设计总监。\n   - 曾任漳州市南靖县县监委委员、南靖县纪委常委、南靖县住房和城乡建设局党组书记、局长，现任漳州市南靖县船场镇党委书记。\n\n4. **赵圣忠**^[3]^\n   - 汉族，1976年12月出生，大学学历，中共党员。\n   - 现任山东省临沂市沂南县医疗保障局党组成员、副局长。\n\n5. **闵圣忠**^[6]^\n   - 曾任江西省监察厅驻省政府办公厅副厅级监察专员，2016年8月被免去该职务。\n\n6. **董圣忠**^[5]^\n   - 现任江西省抚州市东乡区住房和城乡建设局党组成员、副局长。\n\n此外，还有一些可能的人物，如在不同领域有贡献但信息未详尽的“圣忠”，以及可能存在的其他同名人物。\n\n### 地点\n\n- **圣忠林公祠**^[7]^\n  - 位于广东省中山市三乡镇平南村林堡街67号西侧。\n  - 为崇祀平南村林氏先祖圣忠公而建，建于清代。\n  - 是中山现存保存较好、结构布局较完整的清代祠堂建筑之一，具有较高的历史价值和建筑艺术价值。\n\n- **圣忠寺**^[1]^\n  - 位于江西省萍乡市腊市镇凤凰村，五峰山麓。\n\n### 注意\n\n由于“圣忠”是一个较为常见的名字，因此以上列举的人物和地点可能并不全面。同时，由于信息来源的多样性和时效性，以上内容可能存在误差或遗漏。如需更详细或更准确的信息，建议进一步查阅相关资料或咨询专业人士。"
}