{
  "书名": "痘疹定论",
  "朝代": "清",
  "年代": "1713",
  "作者": "朱纯嘏",
  "主要思想": "### 中医《痘疹定论》古籍百科介绍\n\n《痘疹定论》是一部重要的中医古籍，以下是对其的详细介绍：\n\n#### 一、基本信息\n\n- **书名**：《痘疹定论》^[1]^\n- **作者**：朱纯嘏（清代）^[1]^\n- **成书时间**：刊于1713年^[1]^\n- **版本情况**：现有多种近代刊本，1883年徐安澜将本书内容加以增删调整^[1]^\n\n#### 二、内容概述\n\n《痘疹定论》全书共四卷",
  "原文": "### 中医《痘疹定论》古籍百科介绍\n\n《痘疹定论》是一部重要的中医古籍，以下是对其的详细介绍：\n\n#### 一、基本信息\n\n- **书名**：《痘疹定论》^[1]^\n- **作者**：朱纯嘏（清代）^[1]^\n- **成书时间**：刊于1713年^[1]^\n- **版本情况**：现有多种近代刊本，1883年徐安澜将本书内容加以增删调整^[1]^\n\n#### 二、内容概述\n\n《痘疹定论》全书共四卷，内容涵盖了痘疹的各个方面，是中医儿科领域的重要著作。该书详细论述了痘疹的病因、病理、诊断、治疗以及预防等方面的内容，为后世中医儿科的发展提供了宝贵的经验和借鉴。\n\n#### 三、学术价值\n\n- **理论贡献**：《痘疹定论》在中医儿科领域具有重要的理论价值，它系统地总结了痘疹的诊治经验，为中医儿科的发展奠定了坚实的基础。\n- **实践指导**：该书不仅具有理论价值，还具有很高的实践指导意义。书中的治疗方法经过临床验证，具有显著的疗效，为后世中医儿科医生提供了重要的参考。\n\n#### 四、版本与流传\n\n- **版本多样性**：《痘疹定论》在流传过程中形成了多种版本，这些版本在内容上可能存在一定的差异，但都保留了该书的核心思想和主要内容。\n- **流传情况**：该书在中医界具有广泛的影响力，被后世中医儿科医生广泛传阅和学习，为中医儿科的发展做出了重要贡献。\n\n#### 五、总结\n\n《痘疹定论》是一部具有重要学术价值和实践指导意义的中医古籍，它系统地总结了痘疹的诊治经验，为中医儿科的发展提供了宝贵的经验和借鉴。该书在中医界具有广泛的影响力，被后世中医儿科医生广泛传阅和学习，是中医儿科领域不可或缺的重要著作。"
}