{
  "书名": "种痘新书",
  "朝代": "清",
  "年代": "1741",
  "作者": "张琰",
  "主要思想": "# 《种痘新书》百科\n\n《种痘新书》是清代张琰撰写的一部重要儿科类中医著作，以下是对该书的详细介绍：\n\n## 一、基本信息\n\n- **书名**：《种痘新书》\n- **作者**：张琰\n- **成书时间**：刊于1741年^[1]^\n- **卷数**：十二卷^[1]^\n\n## 二、内容概述\n\n《种痘新书》全书共十二卷，内容涵盖了种痘的各个方面，包括但不限于种痘的理论、方法、药方及制法、调治疹症等。该书",
  "原文": "# 《种痘新书》百科\n\n《种痘新书》是清代张琰撰写的一部重要儿科类中医著作，以下是对该书的详细介绍：\n\n## 一、基本信息\n\n- **书名**：《种痘新书》\n- **作者**：张琰\n- **成书时间**：刊于1741年^[1]^\n- **卷数**：十二卷^[1]^\n\n## 二、内容概述\n\n《种痘新书》全书共十二卷，内容涵盖了种痘的各个方面，包括但不限于种痘的理论、方法、药方及制法、调治疹症等。该书对于种痘技术进行了详细的阐述，为当时的儿科医学提供了重要的参考和指导。\n\n## 三、主要特点\n\n- **系统性**：该书系统地介绍了种痘的全过程，从选苗、蓄苗到种痘方法、调治疹症等，都有详尽的论述。\n- **实用性**：书中不仅有理论阐述，还有大量的药方和制法，以及实际案例，具有很强的实用性。\n- **创新性**：在当时，种痘技术还处于探索阶段，《种痘新书》的出版对于推动种痘技术的发展和传播起到了积极的作用。\n\n## 四、影响与意义\n\n- **医学贡献**：《种痘新书》的出版为当时的儿科医学提供了重要的补充和完善，对于提高儿童的健康水平和降低死亡率具有重要意义。\n- **文化传承**：该书作为中医儿科的重要著作之一，对于中医文化的传承和发展也起到了积极的作用。\n- **历史价值**：从历史角度来看，《种痘新书》是研究清代儿科医学和种痘技术的重要资料之一，具有很高的历史价值。\n\n## 五、版本与流传\n\n- **版本信息**：目前存世的《种痘新书》版本可能有所不同，但都以张琰的原著为基础。\n- **流传情况**：该书在清代及以后的医学界产生了广泛的影响，被众多医家所引用和参考。同时，该书也被收入了一些重要的医学丛书和文献库中，为后人所研究和传承。\n\n综上所述，《种痘新书》是清代张琰撰写的一部具有重要价值的儿科类中医著作。该书系统地介绍了种痘的全过程和方法，为当时的儿科医学提供了重要的参考和指导。同时，该书也对于中医文化的传承和发展以及历史研究都具有重要的意义。"
}