{
  "书名": "简要济众方",
  "朝代": "宋",
  "年代": "960",
  "作者": "周应",
  "主要思想": "# 《简要济众方》百科\n\n《简要济众方》是一部具有历史意义的医学方书，以下是对其的详细介绍：\n\n## 一、基本信息\n\n- **书名**：《简要济众方》^[1]^\n- **编撰者**：翰林医官使周应^[1]^\n- **编撰时间**：皇祐初年^[1]^\n- **历史地位**：宋代第4部官修医学方书^[1]^\n\n## 二、内容来源与特点\n\n- **内容来源**：该书内容主要来源于宋初王怀隐等敕撰的《太平",
  "原文": "# 《简要济众方》百科\n\n《简要济众方》是一部具有历史意义的医学方书，以下是对其的详细介绍：\n\n## 一、基本信息\n\n- **书名**：《简要济众方》^[1]^\n- **编撰者**：翰林医官使周应^[1]^\n- **编撰时间**：皇祐初年^[1]^\n- **历史地位**：宋代第4部官修医学方书^[1]^\n\n## 二、内容来源与特点\n\n- **内容来源**：该书内容主要来源于宋初王怀隐等敕撰的《太平圣惠方》以及诸家已试验效名方^[1]^。\n- **特点**：书名中的“简要”二字，暗示了该书内容精炼、实用，旨在方便医者快速查阅和应用有效的方剂。\n\n## 三、历史沿革\n\n- **编撰背景**：宋代医学发展繁荣，官方多次组织编撰医学方书，以推广和传播有效的医疗知识和技术。《简要济众方》正是在这样的背景下应运而生的^[1]^。\n- **散佚时间**：该书约在明末散佚，这对于后世学者来说无疑是一大遗憾^[1]^。\n\n## 四、方剂举例\n\n- **白丁香散**：出自《简要济众方》，具有通血脉、下乳汁的功效，主治妇人吹乳等症状^[4]^。\n- **川楝子散**：同样出自《简要济众方》，用于治疗小肠气痛不可忍及膀胱气冷、结硬不散等症状^[3]^。\n\n## 五、价值与影响\n\n- **医学价值**：《简要济众方》作为一部官修医学方书，其方剂多经过实践验证，具有较高的医学价值。\n- **历史影响**：尽管该书已散佚，但其方剂仍被后世医者所引用和传承，对中医临床实践产生了深远的影响。\n\n综上所述，《简要济众方》是一部具有重要历史地位的医学方书，其精炼实用的内容和经过实践验证的方剂，为中医临床实践提供了宝贵的参考和借鉴。"
}