{
  "书名": "衷中参西录",
  "朝代": "近现代",
  "年代": "1918",
  "作者": "张锡纯",
  "主要思想": "**《衷中参西录》百科**\n\n### 一、基本信息\n\n《衷中参西录》是近现代中国中医学界的医学泰斗张锡纯（1860-1933年）所著的中医典籍^[7][6][5][4][3][2][1]^。该书原从1918年至1934年分七期陆续刊行，全书共三十卷^[7][5]^。此书前三期为处方讲义八卷，后四期分别为药物讲义五卷、医论讲义八卷、医案讲义五卷、伤寒讲义四卷^[5]^。\n\n### 二、作者介绍\n\n张",
  "原文": "**《衷中参西录》百科**\n\n### 一、基本信息\n\n《衷中参西录》是近现代中国中医学界的医学泰斗张锡纯（1860-1933年）所著的中医典籍^[7][6][5][4][3][2][1]^。该书原从1918年至1934年分七期陆续刊行，全书共三十卷^[7][5]^。此书前三期为处方讲义八卷，后四期分别为药物讲义五卷、医论讲义八卷、医案讲义五卷、伤寒讲义四卷^[5]^。\n\n### 二、作者介绍\n\n张锡纯，字寿甫，籍山东诸城，河北省盐山县人，中西医汇通学派的代表人物之一^[6][4]^。1916年在沈阳创办我国第一间中医医院——立达中医院。1926年定居天津，设立“中西汇通医社”，1933年创办国医函授学校，培养了不少中医人才^[6][4]^。\n\n### 三、内容概述\n\n《衷中参西录》以中医理论为基础，同时参考西医理论，对中医的处方、药物、医论、医案以及伤寒等方面进行了深入的探讨和阐述^[5]^。书中内容涵盖了治阴虚劳热、喘息、阳虚、心病、肺病、呕吐、膈食、吐衄、消渴、癃闭、黄疸、淋浊、痢疾等多种疾病的方剂和治法^[7]^。\n\n### 四、版本与出版\n\n- **原版**：该书原从1918年至1934年分七期陆续刊行，每期出版后均有修订^[7][5]^。\n- **2009年版**：由山西科学技术出版社出版^[7]^。\n- **2025年版**：由中国中医药出版社出版，此次整理以每期的最后一版为底本，其余版本为校本，并将其后人于1957年所献张氏遗稿附于最后，对张氏的学术思想和临床经验完整呈现^[5]^。\n\n### 五、学术价值\n\n《衷中参西录》是张锡纯的代表作，其中处方验案多易学易会，屡试屡效，效如桴鼓，为当时及后世医家所公认^[5]^。该书不仅体现了张锡纯深厚的中医功底，还展示了他在中西医汇通方面的独特见解和卓越贡献。\n\n### 六、后世影响\n\n《衷中参西录》的出版和传播对中医界产生了深远的影响。它推动了中西医汇通学派的发展，促进了中医与西医之间的交流与融合。同时，该书也为后世中医临床提供了宝贵的经验和启示。"
}