{
  "书名": "金匮要略释义",
  "朝代": "东汉（此处指原著朝代，释义书本身无特定朝代）",
  "年代": "150",
  "作者": "湖北中医学院",
  "主要思想": "### 《金匮要略释义》百科\n\n《金匮要略释义》是一本对中医经典《金匮要略》进行深入解读和阐释的著作。以下是对该书的详细介绍：\n\n#### 一、基本信息\n\n- **书名**：《金匮要略释义》\n- **作者**：湖北中医学院（也有说法为该书原为中医学院试用教材，具体编著团队可能因版本而异）\n- **出版时间**：不同版本出版时间不同，但该书作为经典教材，有多个版本流传，其中2013年上海科学技术出版",
  "原文": "### 《金匮要略释义》百科\n\n《金匮要略释义》是一本对中医经典《金匮要略》进行深入解读和阐释的著作。以下是对该书的详细介绍：\n\n#### 一、基本信息\n\n- **书名**：《金匮要略释义》\n- **作者**：湖北中医学院（也有说法为该书原为中医学院试用教材，具体编著团队可能因版本而异）\n- **出版时间**：不同版本出版时间不同，但该书作为经典教材，有多个版本流传，其中2013年上海科学技术出版社的版本较为知名\n- **出版社**：上海科学技术出版社等（不同版本出版社可能不同）\n\n#### 二、内容概述\n\n- **整理分段**：该书对《金匮要略》的原文进行了整理分段，使得内容更加清晰易读。\n- **校勘词解**：适加校勘和词解，帮助读者理解原文中的难点和生僻词汇。\n- **通俗阐释**：以通俗易懂的语言对原文进行了阐释，降低了阅读难度，便于初学者和中医爱好者理解。\n- **篇首提示与篇末结语**：每篇篇首均有提示，概括该篇的主要内容；篇末附有结语，总结该篇的要点和精髓，提纲挈领，便于读者领会。\n\n#### 三、书籍特点\n\n- **权威性**：作为中医学院试用教材，该书具有较高的权威性和学术价值。\n- **实用性**：内容详实，阐释清晰，对于中医临床实践和中医教学都具有重要的参考价值。\n- **普及性**：语言通俗易懂，适合中医药院校师生、西医学习中医者及中医自学者或中医药爱好者阅读。\n\n#### 四、书籍目录\n\n该书目录通常包括绪言以及《金匮要略》原文的各篇章，如脏腑经络先后病脉证第一、痉湿喝病脉证治第二、百合狐惑阴阳毒病脉证治第三等，每篇章下又详细列出了具体的方剂和病证^[2]^。\n\n#### 五、相关背景\n\n- **《金匮要略》**：是我国东汉著名医学家张机（字仲景）所著《伤寒杂病论》的杂病部分，也是我国现存最早的一部论述杂病诊治的专书。全书分上、中、下三卷，共25篇，载疾病60余种，收方剂262首^[1]^。\n- **金匮**：在古代，金匮是存放古代帝王圣训和实录的地方，意指本书内容之珍贵^[1]^。\n\n综上所述，《金匮要略释义》是一本对中医经典《金匮要略》进行深入解读和阐释的权威著作，具有较高的学术价值和实用价值，对于中医临床实践和中医教学都具有重要的参考价值。"
}