{
  "书名": "针灸资生经",
  "朝代": "南宋",
  "年代": "1169",
  "作者": "王执中",
  "主要思想": "# 《针灸资生经》百科\n\n《针灸资生经》是一部关于针灸学的古籍，以下是对其的详细介绍：\n\n## 一、基本信息\n\n- **书名**：《针灸资生经》\n- **作者**：王执中（南宋）^[4][1]^\n- **成书时间**：南宋时期^[4][1]^\n- **主要内容**：书中记载了不少临床有效穴位和丰富的灸法，并附有方药，是我国针灸学的重要文献^[4]^。\n\n## 二、作者介绍\n\n- **姓名**：王执",
  "原文": "# 《针灸资生经》百科\n\n《针灸资生经》是一部关于针灸学的古籍，以下是对其的详细介绍：\n\n## 一、基本信息\n\n- **书名**：《针灸资生经》\n- **作者**：王执中（南宋）^[4][1]^\n- **成书时间**：南宋时期^[4][1]^\n- **主要内容**：书中记载了不少临床有效穴位和丰富的灸法，并附有方药，是我国针灸学的重要文献^[4]^。\n\n## 二、作者介绍\n\n- **姓名**：王执中\n- **字**：叔权\n- **籍贯**：浙江瑞安人\n- **生平**：约1140—1207年，南宋乾道五年（1169）中进士，赐从政郎，曾做过将作丞、将作监等小京官，后外调，历任湖南澧州、湖北峡州州学教授。为温州籍最早有医学专著问世、并见诸文献记载的著名针灸医药学家^[4]^。\n- **主要成就**：编撰《针灸资生经》七卷，重视搜录民间医药经验，提出针灸和用药相结合的主张^[4]^。\n\n## 三、书籍内容特点\n\n- **订正错误**：王执中根据临床实践，重新订正针灸典籍的错误^[4]^。\n- **丰富内容**：书中记载了不少临床有效穴位和丰富的灸法，并附有方药^[4]^。\n- **搜录民间经验**：王执中很重视搜录民间医药经验，对民间所掌握的一方一药均加以记录，经反复试用后，把确有疗效的保留下来^[4]^。\n\n## 四、现代出版情况\n\n- **出版信息**：《针灸资生经》在2021年被重新出版，出版社包括湖南科技出版社和中国医药科技出版社等^[5][3]^。\n- **出版形式**：作为《中国针灸大成》丛书的一部分被重新整理出版，该丛书系大型针灸学术资料类编性著作，对我国古今针灸文献分门别类地予以汇集整理，图文并茂^[5]^。\n\n## 五、针灸学背景\n\n- **针灸学定义**：针灸学是以中医理论为指导，研究经络、腧穴及刺灸方法，探讨运用针灸防治疾病规律的一门学科^[2]^。\n- **针灸疗法优点**：具有适应证广、疗效显著、应用方便、经济安全等优点^[2]^。\n- **针灸起源**：针灸疗法大约诞生于新石器时代，具有悠久的历史^[2]^。\n\n《针灸资生经》作为针灸学领域的重要文献，对于研究针灸疗法、经络穴位以及古代医药经验等方面具有重要的参考价值。"
}