{
  "书名": "黄帝内经",
  "朝代": "无（成书于先秦至汉）",
  "年代": "",
  "作者": "无",
  "主要思想": "### 医论、医学古籍百科介绍\n\n#### 一、医论概述\n\n医论，即医学道理或理论的论述，是看病救人所依靠的原理。它涵盖了医学的各个方面，包括疾病的成因、诊断、治疗以及预防等。医论是医学发展的重要组成部分，通过历代医家的不断探讨和实践，逐渐形成了丰富而系统的医学理论体系^[5]^。\n\n#### 二、医学古籍的重要性\n\n医学古籍是医学发展的重要历史见证，它们记录了古代医家对疾病的认知、治疗方法和医学",
  "原文": "### 医论、医学古籍百科介绍\n\n#### 一、医论概述\n\n医论，即医学道理或理论的论述，是看病救人所依靠的原理。它涵盖了医学的各个方面，包括疾病的成因、诊断、治疗以及预防等。医论是医学发展的重要组成部分，通过历代医家的不断探讨和实践，逐渐形成了丰富而系统的医学理论体系^[5]^。\n\n#### 二、医学古籍的重要性\n\n医学古籍是医学发展的重要历史见证，它们记录了古代医家对疾病的认知、治疗方法和医学理论的探索。这些古籍不仅具有历史价值，更对现代医学的发展产生了深远的影响。通过研究医学古籍，我们可以了解古代医学的成就和不足，为现代医学的发展提供有益的借鉴和启示。\n\n#### 三、中医四大经典古籍介绍\n\n中医四大经典指的是在中医发展史上起到重要作用，具有里程碑意义的四部经典巨著，它们对古代乃至现代中医都有着巨大的指导作用与研究价值。这四部经典分别是：\n\n1. **《黄帝内经》**：成书最早，内容最多，是中国医学宝库的经典。它以阴阳五行作为理论基础，通过“望闻问切”四诊合参的方法，探求病因、病性、病位，制定治法，使人体达到阴阳调和而康复^[12][3]^。\n2. **《难经》**：作为中医四大经典之一，对中医理论的发展有着重要贡献。它提出了许多新的医学观点和理论，为后世医家提供了宝贵的参考^[12][1]^。\n3. **《伤寒杂病论》**：以《汤液经法》为基础而成书，对汉字文化圈国家影响深远。它详细论述了伤寒和杂病的病因、病理、诊断和治疗，为中医临床提供了重要的指导^[12][3]^。\n4. **《神农本草经》**：作为中药学的经典之作，它记载了数百种药物的功效和用法，为中药学的发展奠定了基础^[12][1]^。\n\n#### 四、其他重要医学古籍\n\n除了中医四大经典之外，还有许多其他重要的医学古籍值得研究和探讨。例如：\n\n1. **《四部医典》**：藏医学奠基之作，全面反映了藏医学发展的历史轨迹。它涵盖了从基础理论到各科临床实践的各个方面，为藏医学的传播和发展起到了不可替代的作用^[6]^。\n2. **《肯堂医论》**：明代王肯堂所著的医论著作，详细论述了痘疹、惊风等疾病的病因、诊断和治法。它体现了作者的学术见解和临证经验，对后世医家产生了深远的影响^[4]^。\n3. **《医论二则》**：清代程其武等创作的医案医话类中医著作。它论述了诸证多宗古论古法，但能活法妙用，故临证处方每多良效。对奇症怪疴，亦能转危为安^[2]^。\n\n#### 五、总结\n\n医论和医学古籍是医学发展的重要组成部分，它们记录了古代医家对疾病的认知和治疗方法的探索。通过研究这些古籍，我们可以了解古代医学的成就和不足，为现代医学的发展提供有益的借鉴和启示。同时，这些古籍也是中华文化的瑰宝，值得我们珍视和传承。"
}